menu_cpk/__init__.py
menu_cpk/menu.py
menu_cpk-0.5.0.dist-info/METADATA
menu_cpk-0.5.0.dist-info/WHEEL
menu_cpk-0.5.0.dist-info/RECORD
