Metadata-Version: 2.3
Name: menu_cpk
Version: 0.5.0
Summary: menu package
Author: Charles Knell
Author-email: charles1283@gmail.com
Requires-Python: >=3.12
Classifier: Programming Language :: Python :: 3
Classifier: Programming Language :: Python :: 3.12
Classifier: Programming Language :: Python :: 3.13
